py_apple_books/__init__.py
py_apple_books/api.py
py_apple_books/exceptions.py
py_apple_books/utils.py
py_apple_books/db/__init__.py
py_apple_books/db/clause.py
py_apple_books/db/client.py
py_apple_books/db/exceptions.py
py_apple_books/db/query.py
py_apple_books/models/__init__.py
py_apple_books/models/annotation.py
py_apple_books/models/base.py
py_apple_books/models/book.py
py_apple_books/models/collection.py
py_apple_books/models/manager.py
py_apple_books/models/mappings.ini
py_apple_books/models/relations.py
py_apple_books-1.4.0.dist-info/licenses/LICENSE
py_apple_books-1.4.0.dist-info/METADATA
py_apple_books-1.4.0.dist-info/WHEEL
py_apple_books-1.4.0.dist-info/top_level.txt
py_apple_books-1.4.0.dist-info/RECORD
