Metadata-Version: 2.4
Name: py_apple_books
Version: 1.4.0
Summary: Python library for Apple Books
Home-page: https://github.com/vgnshiyer/py-apple-books
Author: Vignesh Iyer
Author-email: vgnshiyer@gmail.com
License: MIT
Classifier: Development Status :: 5 - Production/Stable
Classifier: Intended Audience :: Developers
Classifier: Topic :: Software Development :: Build Tools
Classifier: License :: OSI Approved :: MIT License
Classifier: Programming Language :: Python :: 3
Classifier: Programming Language :: Python :: 3.10
License-File: LICENSE
Dynamic: author
Dynamic: author-email
Dynamic: classifier
Dynamic: description
Dynamic: description-content-type
Dynamic: home-page
Dynamic: license
Dynamic: license-file
Dynamic: summary
